Classfile /home/jatin/jasmin/jasmin-2.4/TEST/JavaCaller/AddInstructions_java.class
  Last modified 23 Jan, 2018; size 270 bytes
  MD5 checksum 9b737e488c529789cfe40fb20872afd1
  Compiled from "AddInstructions_java.java"
public class AddInstructions_java
  minor version: 0
  major version: 52
  flags: ACC_PUBLIC, ACC_SUPER
Constant pool:
   #1 = Methodref          #3.#12         // java/lang/Object."<init>":()V
   #2 = Class              #13            // AddInstructions_java
   #3 = Class              #14            // java/lang/Object
   #4 = Utf8               <init>
   #5 = Utf8               ()V
   #6 = Utf8               Code
   #7 = Utf8               LineNumberTable
   #8 = Utf8               add
   #9 = Utf8               (II)I
  #10 = Utf8               SourceFile
  #11 = Utf8               AddInstructions_java.java
  #12 = NameAndType        #4:#5          // "<init>":()V
  #13 = Utf8               AddInstructions_java
  #14 = Utf8               java/lang/Object
{
  public AddInstructions_java();
    descriptor: ()V
    flags: ACC_PUBLIC
    Code:
      stack=1, locals=1, args_size=1
         0: aload_0
         1: invokespecial #1                  // Method java/lang/Object."<init>":()V
         4: return
      LineNumberTable:
        line 2: 0

  public static int add(int, int);
    descriptor: (II)I
    flags: ACC_PUBLIC, ACC_STATIC
    Code:
      stack=2, locals=2, args_size=2
         0: iload_0
         1: iload_1
         2: iadd
         3: ireturn
      LineNumberTable:
        line 4: 0
}
SourceFile: "AddInstructions_java.java"
